README.md
setup.py
qth_registrar/__init__.py
qth_registrar/registrar.py
qth_registrar/server.py
qth_registrar/tree.py
qth_registrar/version.py
qth_registrar.egg-info/PKG-INFO
qth_registrar.egg-info/SOURCES.txt
qth_registrar.egg-info/dependency_links.txt
qth_registrar.egg-info/entry_points.txt
qth_registrar.egg-info/requires.txt
qth_registrar.egg-info/top_level.txt