Metadata-Version: 1.1
Name: qth-registrar
Version: 0.2.4
Summary: A registration server for Qth
Home-page: https://github.com/mossblaser/qth_registrar
Author: Jonathan Heathcote
Author-email: UNKNOWN
License: GPLv2
Keywords: mqtt asyncio home-automation messaging
Platform: UNKNOWN
Classifier: Development Status :: 3 - Alpha
Classifier: Intended Audience :: Developers
Classifier: License :: OSI Approved :: GNU General Public License v2 (GPLv2)
Classifier: Operating System :: POSIX :: Linux
Classifier: Operating System :: Microsoft :: Windows
Classifier: Operating System :: MacOS
Classifier: Programming Language :: Python :: 3
Classifier: Programming Language :: Python :: 3.4
Classifier: Programming Language :: Python :: 3.5
